{
    "apps": [
        {
            "name": "node-server",
            "script": "npm",
            "args" : "start open"
        },
        {
            "name": "worker-encoder-1",
            "script": "/home/ec2-user/Documents/youtube-video-automator/worker/runWorker.sh",
            "args" : "encoder"
        },
        {
            "name": "worker-uploader-1",
            "script": "/home/ec2-user/Documents/youtube-video-automator/worker/runWorker.sh",
            "args" : "uploader"
        },
        {
            "name": "worker-downloader-1",
            "script": "/home/ec2-user/Documents/youtube-video-automator/worker/runWorker.sh",
            "args" : "downloader"
        },
        {
            "name": "worker-fallback-1",
            "script": "/home/ec2-user/Documents/youtube-video-automator/worker/runWorker.sh",
            "args" : "fallback"
        },
        {
        	"nginx": "nginx-layer",
        	"script": "nginx",
        	"args": "start"
        }
    ]
}